Metadata-Version: 1.1
Name: clorox
Version: 0.6.1
Summary: Removes Xcode's file comment blocks cruft
Home-page: https://github.com/barbosa/clorox
Author: Gustavo Barbosa
Author-email: gustavocsb@gmail.com
License: MIT
Download-URL: https://github.com/barbosa/clorox/tarball/0.6.1
Keywords: xcode,objective-c,swift,ios,macos
Platform: UNKNOWN
